ikaheca/__init__.py
ikaheca/viper.py
ikaheca-0.0.0.dist-info/LICENSE
ikaheca-0.0.0.dist-info/METADATA
ikaheca-0.0.0.dist-info/WHEEL
ikaheca-0.0.0.dist-info/top_level.txt
ikaheca-0.0.0.dist-info/RECORD
