Metadata-Version: 2.1
Name: ikaheca
Version: 0.0.0
Summary: A Python like programming language
Home-page: https://github.com/mbmgfnbk/ikaheca
Author: Felix Bitsch
Author-email: felix.a.bitsch@gmail.com
License: UNKNOWN
Project-URL: Bug Tracker, https://github.com/mbmgfnbk/ikaheca/issues
Platform: UNKNOWN
Classifier: Programming Language :: Python :: 3
Classifier: License :: OSI Approved :: GNU General Public License v3 (GPLv3)
Classifier: Operating System :: OS Independent
Requires-Python: >=3.10
License-File: LICENSE
